mmfunctions/__init__.py
mmfunctions/alert.py
mmfunctions/anomaly.py
mmfunctions/customer.py
mmfunctions/functions.py
mmfunctions/generator.py
mmfunctions/gitanalyzer.py
mmfunctions/pykliep.py
mmfunctions/telemanom.py
mmfunctions/wml_vae_anomaly.py
mmfunctions-0.0.2.1.dist-info/LICENSE
mmfunctions-0.0.2.1.dist-info/METADATA
mmfunctions-0.0.2.1.dist-info/WHEEL
mmfunctions-0.0.2.1.dist-info/top_level.txt
mmfunctions-0.0.2.1.dist-info/RECORD
