Metadata-Version: 2.1
Name: mmfunctions
Version: 0.0.2.1
Summary: Helper package to be used in conjunction with the Maximo Asset Manager pipeline
Home-page: https://github.com/sedgewickmm18/mmfunctions
Author: Markus Müller
Author-email: sedgewickmm18@googlemail.com
License: UNKNOWN
Platform: UNKNOWN
Classifier: Programming Language :: Python :: 3
Classifier: License :: OSI Approved :: MIT License
Classifier: Operating System :: OS Independent
Requires-Python: >=3.6
Requires-Dist: iotfunctions (>=8.2.1)
Requires-Dist: lightgbm (>=3.1.1)
Requires-Dist: matplotlib (==3.1.3)
Requires-Dist: statsmodels (>=0.11.1)
Requires-Dist: torch (>=1.3.1)
Requires-Dist: wiotp-sdk (>=0.11.0)
